nozomi/__init__.py
nozomi/ancillary/__init__.py
nozomi/ancillary/command_line.py
nozomi/ancillary/configuration.py
nozomi/ancillary/database_credentials.py
nozomi/ancillary/file_content.py
nozomi/ancillary/immutable.py
nozomi/ancillary/server_name.py
nozomi/api/__init__.py
nozomi/api/security/__init__.py
nozomi/api/security/session.py
nozomi/app/__init__.py
nozomi/app/security/__init__.py
nozomi/app/security/session.py
nozomi/data/__init__.py
nozomi/data/abstract_encodable.py
nozomi/data/argument_parseable.py
nozomi/data/clocked.py
nozomi/data/codable.py
nozomi/data/datastore.py
nozomi/data/decodable.py
nozomi/data/disposition.py
nozomi/data/encodable.py
nozomi/data/encoder.py
nozomi/data/format.py
nozomi/data/fragment.py
nozomi/data/index_equitable.py
nozomi/data/index_sql_conforming.py
nozomi/data/limit.py
nozomi/data/list_retrievable.py
nozomi/data/named.py
nozomi/data/offset.py
nozomi/data/order.py
nozomi/data/order_by.py
nozomi/data/partial_format.py
nozomi/data/publicly_identified.py
nozomi/data/query.py
nozomi/data/query_string_conforming.py
nozomi/data/sql_conforming.py
nozomi/data/xml.py
nozomi/errors/__init__.py
nozomi/errors/already_exists.py
nozomi/errors/bad_request.py
nozomi/errors/error.py
nozomi/errors/not_authenticated.py
nozomi/errors/not_authorised.py
nozomi/errors/not_found.py
nozomi/errors/too_many_requests.py
nozomi/http/__init__.py
nozomi/http/abstract_headers.py
nozomi/http/accept_language.py
nozomi/http/api_request.py
nozomi/http/character.py
nozomi/http/content_type.py
nozomi/http/headers.py
nozomi/http/method.py
nozomi/http/parseable_data.py
nozomi/http/query_string.py
nozomi/http/redirect.py
nozomi/http/request_body.py
nozomi/http/status_code.py
nozomi/http/url_parameter.py
nozomi/http/url_parameters.py
nozomi/http/user_agent.py
nozomi/rendering/__init__.py
nozomi/rendering/context.py
nozomi/rendering/javascript_class.py
nozomi/rendering/open_graph.py
nozomi/rendering/render_dependency.py
nozomi/rendering/script.py
nozomi-0.0.269.dist-info/METADATA
nozomi-0.0.269.dist-info/WHEEL
nozomi-0.0.269.dist-info/top_level.txt
nozomi-0.0.269.dist-info/RECORD
