Metadata-Version: 2.1
Name: nozomi
Version: 0.0.269
Summary: HTTP web application & API protocol library
Home-page: https://github.com/amatino-code/nozomi
Author: Amatino
Author-email: hugh@blinkybeach.com
License: UNKNOWN
Project-URL: Github Repository, https://github.com/amatino-code/nozomi
Project-URL: About, https://github.com/amatino-code/nozomi
Keywords: library http api web application
Platform: UNKNOWN
Classifier: Development Status :: 2 - Pre-Alpha
Classifier: Intended Audience :: Developers
Classifier: License :: OSI Approved :: MIT License
Classifier: Natural Language :: English
Classifier: Programming Language :: Python :: 3 :: Only
Classifier: Programming Language :: Python :: 3.6
Classifier: Programming Language :: Python :: 3.7
Classifier: Programming Language :: Python :: 3.8
Classifier: Programming Language :: Python :: 3.9
Classifier: Operating System :: OS Independent
Classifier: Topic :: Software Development :: Libraries
Requires-Python: >=3.6
